pyCodeEncryptor/__init__.py
pyCodeEncryptor/pyCodeEncryptor.py
pyCodeEncryptor-0.1.0.dist-info/METADATA
pyCodeEncryptor-0.1.0.dist-info/WHEEL
pyCodeEncryptor-0.1.0.dist-info/top_level.txt
pyCodeEncryptor-0.1.0.dist-info/RECORD
