Metadata-Version: 2.1
Name: pyCodeEncryptor
Version: 0.1.0
Summary: Python için kod şifreleyici//Code encryptor for Python..
Author-email: MAMOSKO <admin@mamoskomail.ml>
Project-URL: Homepage, http://mamosko.ml/pyEncryptor/doc.html
Classifier: Programming Language :: Python :: 3
Classifier: Operating System :: OS Independent
Requires-Python: >=3.8
